nagadpy/__init__.py
nagadpy/exceptions.py
nagadpy/payment.py
nagadpy/payment_verify.py
nagadpy/utils.py
nagadpy/version.py
nagadpy-0.0.2.dist-info/LICENSE
nagadpy-0.0.2.dist-info/METADATA
nagadpy-0.0.2.dist-info/WHEEL
nagadpy-0.0.2.dist-info/RECORD
