Metadata-Version: 2.1
Name: nagadpy
Version: 0.0.2
Summary: Python Package To Handle Nagad Paymant Gateway
License: MIT
Author: MahmudulHassan5809
Author-email: mahmudul.hassan240@gmail.com
Requires-Python: >=3.10,<4.0
Classifier: License :: OSI Approved :: MIT License
Classifier: Programming Language :: Python :: 3
Classifier: Programming Language :: Python :: 3.10
Classifier: Programming Language :: Python :: 3.11
Requires-Dist: cryptography (>=41.0.3,<42.0.0)
Requires-Dist: pytz (>=2023.3.post1,<2024.0)
Requires-Dist: requests (>=2.31.0,<3.0.0)
